ab_core/auth_flow_store/__init__.py
ab_core/auth_flow_store/model.py
ab_core/auth_flow_store/service.py
ab_auth_flow_store-0.1.0.dist-info/METADATA
ab_auth_flow_store-0.1.0.dist-info/WHEEL
ab_auth_flow_store-0.1.0.dist-info/licenses/LICENSE
ab_auth_flow_store-0.1.0.dist-info/RECORD
