Metadata-Version: 2.4
Name: ab-auth-flow-store
Version: 0.1.0
Summary: A template package template.
Author-email: Matt Coulter <mattcoul7@gmail.com>
License-File: LICENSE
Requires-Python: <4.0,>=3.12
